{
  "mangaId": 130429,
  "anilistId": 130429,
  "mangadexId": "f89ed57a-e4c0-48f5-b664-8ef88aa87fd9",
  "title": "I Shall Master this Family!",
  "updatedAt": "2026-04-04T06:58:34.553Z",
  "availableLanguages": [
    "en"
  ],
  "counts": {
    "en": 6
  },
  "languages": {
    "en": [
      {
        "id": "8aff7af9-f1fd-4fc7-8a5f-30fe9f3437ae",
        "title": "",
        "chapter": "183",
        "volume": "4",
        "language": "en",
        "pages": 45,
        "publishedAt": "2025-05-12T11:44:57+00:00",
        "externalUrl": null,
        "scanlationGroup": "ExP Scans",
        "sourceType": "reader"
      },
      {
        "id": "8f41271e-9eab-4e3c-9cba-cec7d0106291",
        "title": "",
        "chapter": "182",
        "volume": "4",
        "language": "en",
        "pages": 25,
        "publishedAt": "2025-05-05T18:24:51+00:00",
        "externalUrl": null,
        "scanlationGroup": "ExP Scans",
        "sourceType": "reader"
      },
      {
        "id": "462300c0-e78e-4af3-a1b6-007991aa29c8",
        "title": "",
        "chapter": "181",
        "volume": "4",
        "language": "en",
        "pages": 55,
        "publishedAt": "2025-04-28T13:14:08+00:00",
        "externalUrl": null,
        "scanlationGroup": "ExP Scans",
        "sourceType": "reader"
      },
      {
        "id": "91054d18-ff93-49ec-9d8d-c2860420acf0",
        "title": "",
        "chapter": "180",
        "volume": "4",
        "language": "en",
        "pages": 40,
        "publishedAt": "2025-04-22T15:13:31+00:00",
        "externalUrl": null,
        "scanlationGroup": "ExP Scans",
        "sourceType": "reader"
      },
      {
        "id": "fa2c2c98-8199-40a6-9258-ee7357536cb1",
        "title": "",
        "chapter": "179",
        "volume": "4",
        "language": "en",
        "pages": 32,
        "publishedAt": "2025-04-07T16:45:32+00:00",
        "externalUrl": null,
        "scanlationGroup": "ExP Scans",
        "sourceType": "reader"
      },
      {
        "id": "8adcf126-b408-4c3a-8713-17523d99162a",
        "title": "",
        "chapter": "178",
        "volume": "4",
        "language": "en",
        "pages": 45,
        "publishedAt": "2025-03-31T15:39:50+00:00",
        "externalUrl": null,
        "scanlationGroup": "ExP Scans",
        "sourceType": "reader"
      }
    ]
  }
}